pybadges/__init__.py
pybadges/__main__.py
pybadges/badge-template-full.svg
pybadges/default-widths.json
pybadges/pil_text_measurer.py
pybadges/precalculate_text.py
pybadges/precalculated_text_measurer.py
pybadges/py.typed
pybadges/text_measurer.py
pybadges/version.py
pybadges-3.0.1.dist-info/LICENSE
pybadges-3.0.1.dist-info/METADATA
pybadges-3.0.1.dist-info/WHEEL
pybadges-3.0.1.dist-info/top_level.txt
pybadges-3.0.1.dist-info/RECORD
