Metadata-Version: 2.1
Name: pybadges
Version: 3.0.1
Summary: A library and command-line tool for generating Github-style badges
Home-page: https://github.com/google/pybadges
Author: Brian Quinlan
Author-email: brian@sweetapp.com
License: Apache-2.0
Keywords: github gh-badges badge shield status
Classifier: Development Status :: 5 - Production/Stable
Classifier: Intended Audience :: Developers
Classifier: Intended Audience :: Developers
Classifier: License :: OSI Approved :: Apache Software License
Classifier: Programming Language :: Python
Classifier: Programming Language :: Python :: 3
Classifier: Programming Language :: Python :: 3.7
Classifier: Programming Language :: Python :: 3.8
Classifier: Programming Language :: Python :: 3.9
Classifier: Programming Language :: Python :: 3.10
Classifier: Programming Language :: Python :: 3.11
Classifier: Programming Language :: Python :: 3.12
Classifier: Operating System :: OS Independent
Requires-Python: >=3.4
Provides-Extra: pil-measurement
Provides-Extra: dev
License-File: LICENSE
